huawei_file_transfer/__init__.py
huawei_file_transfer/custom_huawei.py
huawei_file_transfer/custom_ssh_dispatcher.py
huawei_file_transfer-0.0.2.dist-info/LICENSE.txt
huawei_file_transfer-0.0.2.dist-info/METADATA
huawei_file_transfer-0.0.2.dist-info/WHEEL
huawei_file_transfer-0.0.2.dist-info/top_level.txt
huawei_file_transfer-0.0.2.dist-info/RECORD
