Metadata-Version: 2.1
Name: huawei-file-transfer
Version: 0.0.2
Summary: huawei_file_transfer-V0.0.2 huawei_file_transfer-V0.0.2 is a Netmiko-based function that provides file transfer capabilities for Huawei devices
Home-page: https://github.com/ranmaolin/huawei_file_transfer
Author: RanMaoLin
Author-email: 809780971@qq.com
Classifier: Programming Language :: Python :: 3
Classifier: License :: OSI Approved :: MIT License
Classifier: Operating System :: OS Independent
Requires-Python: >=3.7, <4
License-File: LICENSE.txt
Requires-Dist: netmiko (>=4.2.0)
